[
  {
    "date": "2025-03-27",
    "above50ma": 875,
    "above200ma": 680,
    "total": 1935
  },
  {
    "date": "2025-03-28",
    "above50ma": 635,
    "above200ma": 583,
    "total": 1934
  },
  {
    "date": "2025-03-31",
    "above50ma": 335,
    "above200ma": 411,
    "total": 1935
  },
  {
    "date": "2025-04-01",
    "above50ma": 436,
    "above200ma": 484,
    "total": 1936
  },
  {
    "date": "2025-04-02",
    "above50ma": 473,
    "above200ma": 517,
    "total": 1936
  },
  {
    "date": "2025-04-07",
    "above50ma": 77,
    "above200ma": 172,
    "total": 1936
  },
  {
    "date": "2025-04-08",
    "above50ma": 58,
    "above200ma": 124,
    "total": 1936
  },
  {
    "date": "2025-04-09",
    "above50ma": 32,
    "above200ma": 77,
    "total": 1936
  },
  {
    "date": "2025-04-10",
    "above50ma": 95,
    "above200ma": 174,
    "total": 1936
  },
  {
    "date": "2025-04-11",
    "above50ma": 89,
    "above200ma": 175,
    "total": 1936
  },
  {
    "date": "2025-04-14",
    "above50ma": 100,
    "above200ma": 186,
    "total": 1936
  },
  {
    "date": "2025-04-15",
    "above50ma": 140,
    "above200ma": 243,
    "total": 1936
  },
  {
    "date": "2025-04-16",
    "above50ma": 128,
    "above200ma": 230,
    "total": 1935
  },
  {
    "date": "2025-04-17",
    "above50ma": 136,
    "above200ma": 228,
    "total": 1937
  },
  {
    "date": "2025-04-18",
    "above50ma": 157,
    "above200ma": 238,
    "total": 1937
  },
  {
    "date": "2025-04-21",
    "above50ma": 136,
    "above200ma": 203,
    "total": 1935
  },
  {
    "date": "2025-04-22",
    "above50ma": 131,
    "above200ma": 192,
    "total": 1937
  },
  {
    "date": "2025-04-23",
    "above50ma": 163,
    "above200ma": 233,
    "total": 1937
  },
  {
    "date": "2025-04-24",
    "above50ma": 181,
    "above200ma": 245,
    "total": 1936
  },
  {
    "date": "2025-04-25",
    "above50ma": 211,
    "above200ma": 277,
    "total": 1937
  },
  {
    "date": "2025-04-28",
    "above50ma": 241,
    "above200ma": 282,
    "total": 1936
  },
  {
    "date": "2025-04-29",
    "above50ma": 295,
    "above200ma": 317,
    "total": 1937
  },
  {
    "date": "2025-04-30",
    "above50ma": 278,
    "above200ma": 308,
    "total": 1936
  },
  {
    "date": "2025-05-02",
    "above50ma": 385,
    "above200ma": 345,
    "total": 1937
  },
  {
    "date": "2025-05-05",
    "above50ma": 362,
    "above200ma": 318,
    "total": 1937
  },
  {
    "date": "2025-05-06",
    "above50ma": 408,
    "above200ma": 340,
    "total": 1937
  },
  {
    "date": "2025-05-07",
    "above50ma": 399,
    "above200ma": 333,
    "total": 1936
  },
  {
    "date": "2025-05-08",
    "above50ma": 486,
    "above200ma": 369,
    "total": 1935
  },
  {
    "date": "2025-05-09",
    "above50ma": 543,
    "above200ma": 393,
    "total": 1935
  },
  {
    "date": "2025-05-12",
    "above50ma": 650,
    "above200ma": 427,
    "total": 1938
  },
  {
    "date": "2025-05-13",
    "above50ma": 697,
    "above200ma": 452,
    "total": 1937
  },
  {
    "date": "2025-05-14",
    "above50ma": 847,
    "above200ma": 496,
    "total": 1938
  },
  {
    "date": "2025-05-15",
    "above50ma": 824,
    "above200ma": 492,
    "total": 1936
  },
  {
    "date": "2025-05-16",
    "above50ma": 901,
    "above200ma": 506,
    "total": 1938
  },
  {
    "date": "2025-05-19",
    "above50ma": 815,
    "above200ma": 478,
    "total": 1937
  },
  {
    "date": "2025-05-20",
    "above50ma": 863,
    "above200ma": 485,
    "total": 1938
  },
  {
    "date": "2025-05-21",
    "above50ma": 998,
    "above200ma": 514,
    "total": 1938
  },
  {
    "date": "2025-05-22",
    "above50ma": 966,
    "above200ma": 509,
    "total": 1937
  },
  {
    "date": "2025-05-23",
    "above50ma": 992,
    "above200ma": 517,
    "total": 1938
  },
  {
    "date": "2025-05-26",
    "above50ma": 994,
    "above200ma": 512,
    "total": 1938
  },
  {
    "date": "2025-05-27",
    "above50ma": 937,
    "above200ma": 485,
    "total": 1939
  },
  {
    "date": "2025-05-28",
    "above50ma": 928,
    "above200ma": 478,
    "total": 1939
  },
  {
    "date": "2025-05-29",
    "above50ma": 941,
    "above200ma": 489,
    "total": 1938
  },
  {
    "date": "2025-06-02",
    "above50ma": 765,
    "above200ma": 441,
    "total": 1939
  },
  {
    "date": "2025-06-03",
    "above50ma": 798,
    "above200ma": 452,
    "total": 1939
  },
  {
    "date": "2025-06-04",
    "above50ma": 947,
    "above200ma": 478,
    "total": 1939
  },
  {
    "date": "2025-06-05",
    "above50ma": 974,
    "above200ma": 474,
    "total": 1938
  },
  {
    "date": "2025-06-06",
    "above50ma": 1001,
    "above200ma": 474,
    "total": 1939
  },
  {
    "date": "2025-06-09",
    "above50ma": 998,
    "above200ma": 484,
    "total": 1939
  },
  {
    "date": "2025-06-10",
    "above50ma": 1101,
    "above200ma": 521,
    "total": 1940
  },
  {
    "date": "2025-06-11",
    "above50ma": 1152,
    "above200ma": 536,
    "total": 1940
  },
  {
    "date": "2025-06-12",
    "above50ma": 1208,
    "above200ma": 530,
    "total": 1941
  },
  {
    "date": "2025-06-13",
    "above50ma": 1043,
    "above200ma": 495,
    "total": 1940
  },
  {
    "date": "2025-06-16",
    "above50ma": 1079,
    "above200ma": 509,
    "total": 1942
  },
  {
    "date": "2025-06-17",
    "above50ma": 1110,
    "above200ma": 517,
    "total": 1942
  },
  {
    "date": "2025-06-18",
    "above50ma": 1131,
    "above200ma": 527,
    "total": 1941
  },
  {
    "date": "2025-06-19",
    "above50ma": 944,
    "above200ma": 486,
    "total": 1941
  },
  {
    "date": "2025-06-20",
    "above50ma": 819,
    "above200ma": 471,
    "total": 1942
  },
  {
    "date": "2025-06-23",
    "above50ma": 727,
    "above200ma": 460,
    "total": 1941
  },
  {
    "date": "2025-06-24",
    "above50ma": 916,
    "above200ma": 513,
    "total": 1940
  },
  {
    "date": "2025-06-25",
    "above50ma": 917,
    "above200ma": 524,
    "total": 1942
  },
  {
    "date": "2025-06-26",
    "above50ma": 997,
    "above200ma": 540,
    "total": 1942
  },
  {
    "date": "2025-06-27",
    "above50ma": 1007,
    "above200ma": 554,
    "total": 1942
  },
  {
    "date": "2025-06-30",
    "above50ma": 880,
    "above200ma": 518,
    "total": 1941
  },
  {
    "date": "2025-07-01",
    "above50ma": 945,
    "above200ma": 546,
    "total": 1942
  },
  {
    "date": "2025-07-02",
    "above50ma": 942,
    "above200ma": 563,
    "total": 1942
  },
  {
    "date": "2025-07-03",
    "above50ma": 1036,
    "above200ma": 588,
    "total": 1942
  },
  {
    "date": "2025-07-04",
    "above50ma": 824,
    "above200ma": 550,
    "total": 1942
  },
  {
    "date": "2025-07-07",
    "above50ma": 749,
    "above200ma": 529,
    "total": 1939
  },
  {
    "date": "2025-07-08",
    "above50ma": 666,
    "above200ma": 512,
    "total": 1941
  },
  {
    "date": "2025-07-09",
    "above50ma": 708,
    "above200ma": 532,
    "total": 1941
  },
  {
    "date": "2025-07-10",
    "above50ma": 724,
    "above200ma": 533,
    "total": 1940
  },
  {
    "date": "2025-07-11",
    "above50ma": 798,
    "above200ma": 557,
    "total": 1940
  },
  {
    "date": "2025-07-14",
    "above50ma": 735,
    "above200ma": 531,
    "total": 1940
  },
  {
    "date": "2025-07-15",
    "above50ma": 779,
    "above200ma": 556,
    "total": 1942
  },
  {
    "date": "2025-07-16",
    "above50ma": 812,
    "above200ma": 564,
    "total": 1939
  },
  {
    "date": "2025-07-17",
    "above50ma": 923,
    "above200ma": 602,
    "total": 1942
  },
  {
    "date": "2025-07-18",
    "above50ma": 918,
    "above200ma": 610,
    "total": 1942
  },
  {
    "date": "2025-07-21",
    "above50ma": 925,
    "above200ma": 615,
    "total": 1942
  },
  {
    "date": "2025-07-22",
    "above50ma": 697,
    "above200ma": 536,
    "total": 1943
  },
  {
    "date": "2025-07-23",
    "above50ma": 921,
    "above200ma": 592,
    "total": 1942
  },
  {
    "date": "2025-07-24",
    "above50ma": 940,
    "above200ma": 609,
    "total": 1942
  },
  {
    "date": "2025-07-25",
    "above50ma": 938,
    "above200ma": 598,
    "total": 1943
  },
  {
    "date": "2025-07-28",
    "above50ma": 968,
    "above200ma": 607,
    "total": 1942
  },
  {
    "date": "2025-07-29",
    "above50ma": 858,
    "above200ma": 567,
    "total": 1943
  },
  {
    "date": "2025-07-30",
    "above50ma": 949,
    "above200ma": 600,
    "total": 1941
  },
  {
    "date": "2025-07-31",
    "above50ma": 877,
    "above200ma": 569,
    "total": 1943
  },
  {
    "date": "2025-08-01",
    "above50ma": 47,
    "above200ma": 45,
    "total": 83
  },
  {
    "date": "2025-08-04",
    "above50ma": 1046,
    "above200ma": 639,
    "total": 1942
  },
  {
    "date": "2025-08-05",
    "above50ma": 1155,
    "above200ma": 668,
    "total": 1943
  },
  {
    "date": "2025-08-06",
    "above50ma": 1170,
    "above200ma": 662,
    "total": 1943
  },
  {
    "date": "2025-08-07",
    "above50ma": 1146,
    "above200ma": 676,
    "total": 1943
  },
  {
    "date": "2025-08-08",
    "above50ma": 1127,
    "above200ma": 674,
    "total": 1943
  },
  {
    "date": "2025-08-11",
    "above50ma": 1060,
    "above200ma": 680,
    "total": 1943
  },
  {
    "date": "2025-08-12",
    "above50ma": 1094,
    "above200ma": 696,
    "total": 1943
  },
  {
    "date": "2025-08-13",
    "above50ma": 1086,
    "above200ma": 715,
    "total": 1943
  },
  {
    "date": "2025-08-14",
    "above50ma": 1128,
    "above200ma": 742,
    "total": 1943
  },
  {
    "date": "2025-08-15",
    "above50ma": 1141,
    "above200ma": 766,
    "total": 1943
  },
  {
    "date": "2025-08-18",
    "above50ma": 1157,
    "above200ma": 791,
    "total": 1944
  },
  {
    "date": "2025-08-19",
    "above50ma": 1137,
    "above200ma": 781,
    "total": 1944
  },
  {
    "date": "2025-08-20",
    "above50ma": 1004,
    "above200ma": 702,
    "total": 1944
  },
  {
    "date": "2025-08-21",
    "above50ma": 1106,
    "above200ma": 768,
    "total": 1944
  },
  {
    "date": "2025-08-22",
    "above50ma": 1080,
    "above200ma": 753,
    "total": 1943
  },
  {
    "date": "2025-08-25",
    "above50ma": 1125,
    "above200ma": 788,
    "total": 1945
  },
  {
    "date": "2025-08-26",
    "above50ma": 1130,
    "above200ma": 795,
    "total": 1945
  },
  {
    "date": "2025-08-27",
    "above50ma": 1190,
    "above200ma": 839,
    "total": 1945
  },
  {
    "date": "2025-08-28",
    "above50ma": 1207,
    "above200ma": 848,
    "total": 1944
  },
  {
    "date": "2025-08-29",
    "above50ma": 1186,
    "above200ma": 859,
    "total": 1945
  },
  {
    "date": "2025-09-01",
    "above50ma": 1075,
    "above200ma": 808,
    "total": 1946
  },
  {
    "date": "2025-09-02",
    "above50ma": 1026,
    "above200ma": 792,
    "total": 1946
  },
  {
    "date": "2025-09-03",
    "above50ma": 1096,
    "above200ma": 821,
    "total": 1946
  },
  {
    "date": "2025-09-04",
    "above50ma": 1224,
    "above200ma": 855,
    "total": 1945
  },
  {
    "date": "2025-09-05",
    "above50ma": 1228,
    "above200ma": 874,
    "total": 1946
  },
  {
    "date": "2025-09-08",
    "above50ma": 1238,
    "above200ma": 893,
    "total": 1946
  },
  {
    "date": "2025-09-09",
    "above50ma": 1193,
    "above200ma": 895,
    "total": 1946
  },
  {
    "date": "2025-09-10",
    "above50ma": 1180,
    "above200ma": 887,
    "total": 1946
  },
  {
    "date": "2025-09-11",
    "above50ma": 1014,
    "above200ma": 821,
    "total": 1947
  },
  {
    "date": "2025-09-12",
    "above50ma": 1063,
    "above200ma": 844,
    "total": 1947
  },
  {
    "date": "2025-09-15",
    "above50ma": 1033,
    "above200ma": 838,
    "total": 1947
  },
  {
    "date": "2025-09-16",
    "above50ma": 1064,
    "above200ma": 861,
    "total": 1945
  },
  {
    "date": "2025-09-17",
    "above50ma": 1049,
    "above200ma": 865,
    "total": 1947
  },
  {
    "date": "2025-09-18",
    "above50ma": 1118,
    "above200ma": 910,
    "total": 1948
  },
  {
    "date": "2025-09-19",
    "above50ma": 1106,
    "above200ma": 924,
    "total": 1948
  },
  {
    "date": "2025-09-22",
    "above50ma": 1094,
    "above200ma": 916,
    "total": 1946
  },
  {
    "date": "2025-09-23",
    "above50ma": 1042,
    "above200ma": 900,
    "total": 1947
  },
  {
    "date": "2025-09-24",
    "above50ma": 1032,
    "above200ma": 899,
    "total": 1948
  },
  {
    "date": "2025-09-25",
    "above50ma": 1055,
    "above200ma": 918,
    "total": 1947
  },
  {
    "date": "2025-09-26",
    "above50ma": 842,
    "above200ma": 838,
    "total": 1947
  },
  {
    "date": "2025-09-30",
    "above50ma": 967,
    "above200ma": 885,
    "total": 1947
  },
  {
    "date": "2025-10-01",
    "above50ma": 945,
    "above200ma": 871,
    "total": 1947
  },
  {
    "date": "2025-10-02",
    "above50ma": 882,
    "above200ma": 861,
    "total": 1946
  },
  {
    "date": "2025-10-03",
    "above50ma": 869,
    "above200ma": 861,
    "total": 1946
  },
  {
    "date": "2025-10-07",
    "above50ma": 887,
    "above200ma": 891,
    "total": 1949
  },
  {
    "date": "2025-10-08",
    "above50ma": 886,
    "above200ma": 896,
    "total": 1949
  },
  {
    "date": "2025-10-09",
    "above50ma": 871,
    "above200ma": 893,
    "total": 1949
  },
  {
    "date": "2025-10-13",
    "above50ma": 765,
    "above200ma": 842,
    "total": 1948
  },
  {
    "date": "2025-10-14",
    "above50ma": 637,
    "above200ma": 790,
    "total": 1948
  },
  {
    "date": "2025-10-15",
    "above50ma": 673,
    "above200ma": 817,
    "total": 1948
  },
  {
    "date": "2025-10-16",
    "above50ma": 745,
    "above200ma": 844,
    "total": 1949
  },
  {
    "date": "2025-10-17",
    "above50ma": 714,
    "above200ma": 832,
    "total": 1946
  },
  {
    "date": "2025-10-20",
    "above50ma": 720,
    "above200ma": 843,
    "total": 1948
  },
  {
    "date": "2025-10-21",
    "above50ma": 753,
    "above200ma": 853,
    "total": 1948
  },
  {
    "date": "2025-10-22",
    "above50ma": 824,
    "above200ma": 893,
    "total": 1948
  },
  {
    "date": "2025-10-23",
    "above50ma": 793,
    "above200ma": 876,
    "total": 1948
  },
  {
    "date": "2025-10-27",
    "above50ma": 788,
    "above200ma": 871,
    "total": 1948
  },
  {
    "date": "2025-10-28",
    "above50ma": 709,
    "above200ma": 838,
    "total": 1949
  },
  {
    "date": "2025-10-29",
    "above50ma": 724,
    "above200ma": 844,
    "total": 1948
  },
  {
    "date": "2025-10-30",
    "above50ma": 686,
    "above200ma": 827,
    "total": 1948
  },
  {
    "date": "2025-10-31",
    "above50ma": 681,
    "above200ma": 823,
    "total": 1949
  },
  {
    "date": "2025-11-03",
    "above50ma": 686,
    "above200ma": 825,
    "total": 1948
  },
  {
    "date": "2025-11-04",
    "above50ma": 588,
    "above200ma": 778,
    "total": 1946
  },
  {
    "date": "2025-11-05",
    "above50ma": 566,
    "above200ma": 777,
    "total": 1948
  },
  {
    "date": "2025-11-06",
    "above50ma": 646,
    "above200ma": 806,
    "total": 1947
  },
  {
    "date": "2025-11-07",
    "above50ma": 613,
    "above200ma": 773,
    "total": 1947
  },
  {
    "date": "2025-11-10",
    "above50ma": 580,
    "above200ma": 770,
    "total": 1947
  },
  {
    "date": "2025-11-11",
    "above50ma": 594,
    "above200ma": 759,
    "total": 1949
  },
  {
    "date": "2025-11-12",
    "above50ma": 669,
    "above200ma": 806,
    "total": 1950
  },
  {
    "date": "2025-11-13",
    "above50ma": 702,
    "above200ma": 810,
    "total": 1947
  },
  {
    "date": "2025-11-14",
    "above50ma": 644,
    "above200ma": 775,
    "total": 1950
  },
  {
    "date": "2025-11-17",
    "above50ma": 562,
    "above200ma": 735,
    "total": 1952
  },
  {
    "date": "2025-11-18",
    "above50ma": 449,
    "above200ma": 668,
    "total": 1953
  },
  {
    "date": "2025-11-19",
    "above50ma": 414,
    "above200ma": 645,
    "total": 1953
  },
  {
    "date": "2025-11-20",
    "above50ma": 513,
    "above200ma": 699,
    "total": 1954
  },
  {
    "date": "2025-11-21",
    "above50ma": 412,
    "above200ma": 633,
    "total": 1952
  },
  {
    "date": "2025-11-24",
    "above50ma": 490,
    "above200ma": 667,
    "total": 1953
  },
  {
    "date": "2025-11-25",
    "above50ma": 526,
    "above200ma": 694,
    "total": 1954
  },
  {
    "date": "2025-11-26",
    "above50ma": 641,
    "above200ma": 765,
    "total": 1954
  },
  {
    "date": "2025-11-27",
    "above50ma": 668,
    "above200ma": 777,
    "total": 1953
  },
  {
    "date": "2025-11-28",
    "above50ma": 729,
    "above200ma": 798,
    "total": 1953
  },
  {
    "date": "2025-12-01",
    "above50ma": 692,
    "above200ma": 780,
    "total": 1952
  },
  {
    "date": "2025-12-02",
    "above50ma": 731,
    "above200ma": 780,
    "total": 1953
  },
  {
    "date": "2025-12-03",
    "above50ma": 802,
    "above200ma": 809,
    "total": 1954
  },
  {
    "date": "2025-12-04",
    "above50ma": 836,
    "above200ma": 810,
    "total": 1952
  },
  {
    "date": "2025-12-05",
    "above50ma": 809,
    "above200ma": 805,
    "total": 1952
  },
  {
    "date": "2025-12-08",
    "above50ma": 829,
    "above200ma": 820,
    "total": 1954
  },
  {
    "date": "2025-12-09",
    "above50ma": 821,
    "above200ma": 816,
    "total": 1952
  },
  {
    "date": "2025-12-10",
    "above50ma": 810,
    "above200ma": 818,
    "total": 1952
  },
  {
    "date": "2025-12-11",
    "above50ma": 779,
    "above200ma": 807,
    "total": 1954
  },
  {
    "date": "2025-12-12",
    "above50ma": 833,
    "above200ma": 828,
    "total": 1953
  },
  {
    "date": "2025-12-15",
    "above50ma": 848,
    "above200ma": 845,
    "total": 1954
  },
  {
    "date": "2025-12-16",
    "above50ma": 754,
    "above200ma": 814,
    "total": 1955
  },
  {
    "date": "2025-12-17",
    "above50ma": 757,
    "above200ma": 818,
    "total": 1955
  },
  {
    "date": "2025-12-18",
    "above50ma": 738,
    "above200ma": 800,
    "total": 1953
  },
  {
    "date": "2025-12-19",
    "above50ma": 824,
    "above200ma": 841,
    "total": 1954
  },
  {
    "date": "2025-12-22",
    "above50ma": 932,
    "above200ma": 865,
    "total": 1955
  },
  {
    "date": "2025-12-23",
    "above50ma": 923,
    "above200ma": 862,
    "total": 1955
  },
  {
    "date": "2025-12-24",
    "above50ma": 900,
    "above200ma": 857,
    "total": 1956
  },
  {
    "date": "2025-12-26",
    "above50ma": 899,
    "above200ma": 876,
    "total": 1956
  },
  {
    "date": "2025-12-29",
    "above50ma": 960,
    "above200ma": 900,
    "total": 1954
  },
  {
    "date": "2025-12-30",
    "above50ma": 926,
    "above200ma": 876,
    "total": 1955
  },
  {
    "date": "2025-12-31",
    "above50ma": 917,
    "above200ma": 881,
    "total": 1956
  },
  {
    "date": "2026-01-02",
    "above50ma": 954,
    "above200ma": 897,
    "total": 1956
  },
  {
    "date": "2026-01-05",
    "above50ma": 844,
    "above200ma": 851,
    "total": 1955
  },
  {
    "date": "2026-01-06",
    "above50ma": 891,
    "above200ma": 883,
    "total": 1955
  },
  {
    "date": "2026-01-07",
    "above50ma": 991,
    "above200ma": 944,
    "total": 1955
  },
  {
    "date": "2026-01-08",
    "above50ma": 937,
    "above200ma": 925,
    "total": 1955
  },
  {
    "date": "2026-01-09",
    "above50ma": 979,
    "above200ma": 926,
    "total": 1955
  },
  {
    "date": "2026-01-12",
    "above50ma": 1086,
    "above200ma": 962,
    "total": 1955
  },
  {
    "date": "2026-01-13",
    "above50ma": 1051,
    "above200ma": 965,
    "total": 1955
  },
  {
    "date": "2026-01-14",
    "above50ma": 1253,
    "above200ma": 1058,
    "total": 1954
  },
  {
    "date": "2026-01-15",
    "above50ma": 1279,
    "above200ma": 1075,
    "total": 1955
  },
  {
    "date": "2026-01-16",
    "above50ma": 1275,
    "above200ma": 1087,
    "total": 1955
  },
  {
    "date": "2026-01-19",
    "above50ma": 1296,
    "above200ma": 1127,
    "total": 1956
  },
  {
    "date": "2026-01-20",
    "above50ma": 1276,
    "above200ma": 1107,
    "total": 1956
  },
  {
    "date": "2026-01-21",
    "above50ma": 1183,
    "above200ma": 1054,
    "total": 1956
  },
  {
    "date": "2026-01-22",
    "above50ma": 1216,
    "above200ma": 1081,
    "total": 1956
  },
  {
    "date": "2026-01-23",
    "above50ma": 1244,
    "above200ma": 1103,
    "total": 1956
  },
  {
    "date": "2026-01-26",
    "above50ma": 1284,
    "above200ma": 1135,
    "total": 1955
  },
  {
    "date": "2026-01-27",
    "above50ma": 1278,
    "above200ma": 1122,
    "total": 1956
  },
  {
    "date": "2026-01-28",
    "above50ma": 1280,
    "above200ma": 1103,
    "total": 1955
  },
  {
    "date": "2026-01-29",
    "above50ma": 1171,
    "above200ma": 1055,
    "total": 1954
  },
  {
    "date": "2026-01-30",
    "above50ma": 983,
    "above200ma": 976,
    "total": 1956
  },
  {
    "date": "2026-02-02",
    "above50ma": 789,
    "above200ma": 894,
    "total": 1956
  },
  {
    "date": "2026-02-03",
    "above50ma": 838,
    "above200ma": 914,
    "total": 1954
  },
  {
    "date": "2026-02-04",
    "above50ma": 968,
    "above200ma": 980,
    "total": 1954
  },
  {
    "date": "2026-02-05",
    "above50ma": 895,
    "above200ma": 945,
    "total": 1956
  },
  {
    "date": "2026-02-06",
    "above50ma": 737,
    "above200ma": 874,
    "total": 1956
  },
  {
    "date": "2026-02-09",
    "above50ma": 793,
    "above200ma": 879,
    "total": 1956
  },
  {
    "date": "2026-02-10",
    "above50ma": 812,
    "above200ma": 900,
    "total": 1956
  },
  {
    "date": "2026-02-11",
    "above50ma": 844,
    "above200ma": 909,
    "total": 1956
  },
  {
    "date": "2026-02-23",
    "above50ma": 1076,
    "above200ma": 1002,
    "total": 1956
  },
  {
    "date": "2026-02-24",
    "above50ma": 1093,
    "above200ma": 1000,
    "total": 1956
  },
  {
    "date": "2026-02-25",
    "above50ma": 1083,
    "above200ma": 1006,
    "total": 1956
  },
  {
    "date": "2026-02-26",
    "above50ma": 1135,
    "above200ma": 1038,
    "total": 1956
  },
  {
    "date": "2026-03-02",
    "above50ma": 1094,
    "above200ma": 1021,
    "total": 1956
  },
  {
    "date": "2026-03-03",
    "above50ma": 922,
    "above200ma": 956,
    "total": 1955
  },
  {
    "date": "2026-03-04",
    "above50ma": 600,
    "above200ma": 805,
    "total": 1955
  },
  {
    "date": "2026-03-05",
    "above50ma": 721,
    "above200ma": 885,
    "total": 1956
  },
  {
    "date": "2026-03-06",
    "above50ma": 793,
    "above200ma": 916,
    "total": 1956
  },
  {
    "date": "2026-03-09",
    "above50ma": 510,
    "above200ma": 754,
    "total": 1956
  },
  {
    "date": "2026-03-10",
    "above50ma": 605,
    "above200ma": 820,
    "total": 1955
  },
  {
    "date": "2026-03-11",
    "above50ma": 777,
    "above200ma": 901,
    "total": 1956
  },
  {
    "date": "2026-03-12",
    "above50ma": 745,
    "above200ma": 902,
    "total": 1955
  },
  {
    "date": "2026-03-13",
    "above50ma": 755,
    "above200ma": 888,
    "total": 1956
  },
  {
    "date": "2026-03-16",
    "above50ma": 796,
    "above200ma": 901,
    "total": 1956
  },
  {
    "date": "2026-03-17",
    "above50ma": 862,
    "above200ma": 937,
    "total": 1956
  },
  {
    "date": "2026-03-18",
    "above50ma": 888,
    "above200ma": 962,
    "total": 1956
  },
  {
    "date": "2026-03-19",
    "above50ma": 821,
    "above200ma": 915,
    "total": 1955
  },
  {
    "date": "2026-03-20",
    "above50ma": 833,
    "above200ma": 923,
    "total": 1954
  },
  {
    "date": "2026-03-23",
    "above50ma": 700,
    "above200ma": 860,
    "total": 1954
  },
  {
    "date": "2026-03-24",
    "above50ma": 674,
    "above200ma": 861,
    "total": 1955
  },
  {
    "date": "2026-03-25",
    "above50ma": 787,
    "above200ma": 910,
    "total": 1955
  },
  {
    "date": "2026-03-26",
    "above50ma": 762,
    "above200ma": 891,
    "total": 1956
  },
  {
    "date": "2026-03-27",
    "above50ma": 738,
    "above200ma": 901,
    "total": 1952
  }
]